[
  {
    "id": "3918c558-0c61-491c-b983-b940c3a0dbe0",
    "data": [
      {
        "text": "Is this the website for ",
        "userDefined": false
      },
      {
        "text": "Virtual Labs",
        "meta": "@sys.ignore",
        "userDefined": false
      },
      {
        "text": "?",
        "userDefined": false
      }
    ],
    "isTemplate": false,
    "count": 0,
    "lang": "en",
    "updated": 0
  },
  {
    "id": "41c5acc8-4126-40af-b130-85925b4dd37c",
    "data": [
      {
        "text": "Is this ",
        "userDefined": false
      },
      {
        "text": "Virtual Lab",
        "meta": "@sys.ignore",
        "userDefined": false
      },
      {
        "text": "?",
        "userDefined": false
      }
    ],
    "isTemplate": false,
    "count": 0,
    "lang": "en",
    "updated": 0
  },
  {
    "id": "27c45c69-9010-48ce-bd6a-4565f0fd3621",
    "data": [
      {
        "text": "Am I at ",
        "userDefined": false
      },
      {
        "text": "Virtual Labs",
        "meta": "@sys.ignore",
        "userDefined": false
      },
      {
        "text": "?",
        "userDefined": false
      }
    ],
    "isTemplate": false,
    "count": 0,
    "lang": "en",
    "updated": 0
  },
  {
    "id": "697b8f69-fadb-4209-a55a-381eda8b1863",
    "data": [
      {
        "text": "Is this ",
        "userDefined": false
      },
      {
        "text": "Virtual Labs",
        "meta": "@sys.ignore",
        "userDefined": false
      },
      {
        "text": "?",
        "userDefined": false
      }
    ],
    "isTemplate": false,
    "count": 0,
    "lang": "en",
    "updated": 0
  }
]